colorengine/__init__.py
colorengine/_version.py
colorengine/__pycache__/__init__.cpython-312.pyc
colorengine/colormaps/__init__.py
colorengine/colormaps/discrete_defaults.py
colorengine/colormaps/distinct.py
colorengine/colormaps/dream.py
colorengine/colormaps/french.py
colorengine/colormaps/icecream.py
colorengine/colormaps/vivid.py
colorengine/colormaps/warm.py
colorengine/colormaps/__pycache__/__init__.cpython-312.pyc
colorengine/colormaps/__pycache__/discrete_defaults.cpython-312.pyc
colorengine/colormaps/__pycache__/vivid.cpython-312.pyc
colorengine-0.2.3.dist-info/LICENSE
colorengine-0.2.3.dist-info/METADATA
colorengine-0.2.3.dist-info/WHEEL
colorengine-0.2.3.dist-info/top_level.txt
colorengine-0.2.3.dist-info/RECORD
